i2s/i2s_loop/synth/i2s_reader.vhd
-- I2S Reader en mode esclave + receiver

library ieee;
use ieee.std_logic_1164.all;
use ieee.numeric_std.all;

entity i2s_reader is
	generic(
		DATA_LENGTH	: INTEGER := 32	-- taille des données
	);
	port(
		reset_n	: in	std_logic;
		clk	  	: in	std_logic;

		data		: out	std_logic_vector((DATA_LENGTH-1) downto 0);

		mclk		: out	std_logic;	  -- clock du systeme
		sclk		: out 	std_logic;	-- frequence din
		lrclk		: out 	std_logic;	-- left / right
		din	  	: in 	std_logic	    -- sortie de l'ADC
	);
end entity i2s_reader;

architecture arc_i2s_reader of i2s_reader is

type t_etat is (etat0, etat1, etat2, etat3);
signal etat : t_etat;

signal counter		  : integer range 0 to DATA_LENGTH;
signal counter_clk	: unsigned (7 downto 0);

signal sclk_old	    : std_logic;
signal sclk_cur	    : std_logic;
signal lrclk_old   	: std_logic;
signal lrclk_cur   	: std_logic;

signal reg_data	: std_logic_vector((DATA_LENGTH - 1) downto 0);

begin

 -- Process synchrone --
process (clk, reset_n)
begin
  	if reset_n = '0' then
    		etat <= etat0;

      		counter_clk <= (others => '0');
		counter     <= 0;
		reg_data    <= (others => '0');
		data        <= (others => '0');

    		sclk_old    <= '0';
    		sclk_cur    <= '0';
    		lrclk_old   <= '0';
    		lrclk_cur   <= '0';

  	elsif clk'event and clk='1' then
    		counter_clk <= counter_clk + 1;

    		sclk_old    <= sclk_cur;
      	sclk_cur    <= not(counter_clk(1));
      	lrclk_old   <= lrclk_cur;
      	lrclk_cur   <= counter_clk(7);

	    	case etat is
			when etat0 =>
				reg_data <= (others => '0');
				counter  <= 0;
				if(lrclk_old = '1' and lrclk_cur = '0') then
					etat <= etat1;
				else
					etat <= etat0;
				end if;
			when etat1 =>
				if(sclk_old = '0' and sclk_cur = '1') then
					etat <= etat2;
				else
					etat <= etat1;
				end if;
			when etat2 =>
				if(sclk_old = '0' and sclk_cur = '1') then
					reg_data <= reg_data(reg_data'length-2 downto 0) & din;
					counter  <= counter + 1;
				else end if;
				if( counter = DATA_LENGTH)  then
					counter <= 0;
					etat <= etat3;
				else
					etat <= etat2;
				end if;
			when etat3 =>
				data <= reg_data;
				if(sclk_old = '0' and sclk_cur = '1') then
					etat <= etat0;
				else
					etat <= etat3;
				end if;
	 	end case;
  	end if;
end process;

mclk   <= clk;
sclk   <= sclk_old;
lrclk  <= lrclk_old;

end arc_i2s_reader;

i2s/i2s_reader/sim/i2s_reader_tb.vhd
library ieee;
use ieee.std_logic_1164.all;

entity i2s_reader_tb is
end i2s_reader_tb;

architecture arc_i2s_reader_tb of i2s_reader_tb is

  signal reset_n, clk : std_logic;
  signal mclk, sclk, lrclk, din : std_logic;
  signal data : std_logic_vector(15 downto 0);

  constant clock_t : time :=  44.288941 ns;

begin


  i2s_reader : entity work.i2s_reader port map (	reset_n => reset_n,
  							clk     => clk,
  							data    => data,
      							mclk    => mclk,
      							sclk    => sclk, 
      							lrclk   => lrclk,
      							din     => din
      						 );

  clock_p : process begin
      clk <= '0';
      wait for clock_t;
      clk <= '1';
      wait for clock_t;
  end process;

  rst_p : process begin
      reset_n <= '0';
      wait for clock_t;
      reset_n <= '1';
      wait for 50 us;
      wait;
  end process;

  din_p : process begin
    wait until rising_edge(sclk);
    din <= '0';
    wait until rising_edge(sclk);
    din <= '1';
    wait until rising_edge(sclk);
    din <= '0';
    wait until rising_edge(sclk);
    din <= '1';
    wait until rising_edge(sclk);
    din <= '1';
    wait until rising_edge(sclk);
    din <= '0';
    wait until rising_edge(sclk);
    din <= '0';
    wait until rising_edge(sclk);
    din <= '0';
  end process;

end arc_i2s_reader_tb;

i2s/i2s_reader/i2s_reader_tb.vcd
$date
  Thu Dec 31 17:19:42 2020
$end
$version
  GHDL v0
$end
$timescale
  1 fs
$end
$scope module standard $end
$upscope $end
$scope module std_logic_1164 $end
$upscope $end
$scope module numeric_std $end
$upscope $end
$scope module i2s_reader_tb $end
$var reg 1 ! reset_n $end
$var reg 1 " clk $end
$var reg 1 # mclk $end
$var reg 1 $ sclk $end
$var reg 1 % lrclk $end
$var reg 1 & din $end
$var reg 16 ' data[15:0] $end
$scope module i2s_reader $end
$var reg 1 ( reset_n $end
$var reg 1 ) clk $end
$var reg 16 * data[15:0] $end
$var reg 1 + mclk $end
$var reg 1 , sclk $end
$var reg 1 - lrclk $end
$var reg 1 . din $end
$comment etat is not handled $end
$var integer 32 / counter $end
$var reg 8 0 counter_clk[7:0] $end
$var reg 1 1 sclk_old $end
$var reg 1 2 sclk_cur $end
$var reg 1 3 lrclk_old $end
$var reg 1 4 lrclk_cur $end
$var reg 16 5 reg_data[15:0] $end
$upscope $end
$upscope $end
$enddefinitions $end
#0
0!
0"
0#
0$
0%
U&
bUUUUUUUUUUUUUUUU '
0(
0)
bUUUUUUUUUUUUUUUU *
0+
0,
0-
U.
b0 /
b00000000 0
01
02
03
04
b0000000000000000 5
#44288941
1!
1"
1#
1(
1)
1+
b00000001 0
12
#88577882
0"
0#
0)
0+
#132866823
1"
1#
1$
0&
1)
1+
1,
0.
b00000010 0
11
#177155764
0"
0#
0)
0+
#221444705
1"
1#
1)
1+
b00000011 0
02
#265733646
0"
0#
0)
0+
#310022587
1"
1#
0$
1)
1+
0,
b00000100 0
01
#354311528
0"
0#
0)
0+
#398600469
1"
1#
1)
1+
b00000101 0
12
#442889410
0"
0#
0)
0+
#487178351
1"
1#
1$
1&
1)
1+
1,
1.
b00000110 0
11
#531467292
0"
0#
0)
0+
#575756233
1"
1#
1)
1+
b00000111 0
02
#620045174
0"
0#
0)
0+
#664334115
1"
1#
0$
1)
1+
0,
b00001000 0
01
#708623056
0"
0#
0)
0+
#752911997
1"
1#
1)
1+
b00001001 0
12
#797200938
0"
0#
0)
0+
#841489879
1"
1#
1$
0&
1)
1+
1,
0.
b00001010 0
11
#885778820
0"
0#
0)
0+
#930067761
1"
1#
1)
1+
b00001011 0
02
#974356702
0"
0#
0)
0+
#1018645643
1"
1#
0$
1)
1+
0,
b00001100 0
01
#1062934584
0"
0#
0)
0+
#1107223525
1"
1#
1)
1+
b00001101 0
12
#1151512466
0"
0#
0)
0+
#1195801407
1"
1#
1$
1&
1)
1+
1,
1.
b00001110 0
11
#1240090348
0"
0#
0)
0+
#1284379289
1"
1#
1)
1+
b00001111 0
02
#1328668230
0"
0#
0)
0+
#1372957171
1"
1#
0$
1)
1+
0,
b00010000 0
01
#1417246112
0"
0#
0)
0+
#1461535053
1"
1#
1)
1+
b00010001 0
12
#1505823994
0"
0#
0)
0+
#1550112935
1"
1#
1$
1)
1+
1,
b00010010 0
11
#1594401876
0"
0#
0)
0+
#1638690817
1"
1#
1)
1+
b00010011 0
02
#1682979758
0"
0#
0)
0+
#1727268699
1"
1#
0$
1)
1+
0,
b00010100 0
01
#1771557640
0"
0#
0)
0+
#1815846581
1"
1#
1)
1+
b00010101 0
12
#1860135522
0"
0#
0)
0+
#1904424463
1"
1#
1$
0&
1)
1+
1,
0.
b00010110 0
11
#1948713404
0"
0#
0)
0+
#1993002345
1"
1#
1)
1+
b00010111 0
02
#2037291286
0"
0#
0)
0+
#2081580227
1"
1#
0$
1)
1+
0,
b00011000 0
01
#2125869168
0"
0#
0)
0+
#2170158109
1"
1#
1)
1+
b00011001 0
12
#2214447050
0"
0#
0)
0+
#2258735991
1"
1#
1$
1)
1+
1,
b00011010 0
11
#2303024932
0"
0#
0)
0+
#2347313873
1"
1#
1)
1+
b00011011 0
02
#2391602814
0"
0#
0)
0+
#2435891755
1"
1#
0$
1)
1+
0,
b00011100 0
01
#2480180696
0"
0#
0)
0+
#2524469637
1"
1#
1)
1+
b00011101 0
12
#2568758578
0"
0#
0)
0+
#2613047519
1"
1#
1$
1)
1+
1,
b00011110 0
11
#2657336460
0"
0#
0)
0+
#2701625401
1"
1#
1)
1+
b00011111 0
02
#2745914342
0"
0#
0)
0+
#2790203283
1"
1#
0$
1)
1+
0,
b00100000 0
01
#2834492224
0"
0#
0)
0+
#2878781165
1"
1#
1)
1+
b00100001 0
12
#2923070106
0"
0#
0)
0+
#2967359047
1"
1#
1$
1)
1+
1,
b00100010 0
11
#3011647988
0"
0#
0)
0+
#3055936929
1"
1#
1)
1+
b00100011 0
02
#3100225870
0"
0#
0)
0+
#3144514811
1"
1#
0$
1)
1+
0,
b00100100 0
01
#3188803752
0"
0#
0)
0+
#3233092693
1"
1#
1)
1+
b00100101 0
12
#3277381634
0"
0#
0)
0+
#3321670575
1"
1#
1$
1&
1)
1+
1,
1.
b00100110 0
11
#3365959516
0"
0#
0)
0+
#3410248457
1"
1#
1)
1+
b00100111 0
02
#3454537398
0"
0#
0)
0+
#3498826339
1"
1#
0$
1)
1+
0,
b00101000 0
01
#3543115280
0"
0#
0)
0+
#3587404221
1"
1#
1)
1+
b00101001 0
12
#3631693162
0"
0#
0)
0+
#3675982103
1"
1#
1$
0&
1)
1+
1,
0.
b00101010 0
11
#3720271044
0"
0#
0)
0+
#3764559985
1"
1#
1)
1+
b00101011 0
02
#3808848926
0"
0#
0)
0+
#3853137867
1"
1#
0$
1)
1+
0,
b00101100 0
01
#3897426808
0"
0#
0)
0+
#3941715749
1"
1#
1)
1+
b00101101 0
12
#3986004690
0"
0#
0)
0+
#4030293631
1"
1#
1$
1&
1)
1+
1,
1.
b00101110 0
11
#4074582572
0"
0#
0)
0+
#4118871513
1"
1#
1)
1+
b00101111 0
02
#4163160454
0"
0#
0)
0+
#4207449395
1"
1#
0$
1)
1+
0,
b00110000 0
01
#4251738336
0"
0#
0)
0+
#4296027277
1"
1#
1)
1+
b00110001 0
12
#4340316218
0"
0#
0)
0+
#4384605159
1"
1#
1$
1)
1+
1,
b00110010 0
11
#4428894100
0"
0#
0)
0+
#4473183041
1"
1#
1)
1+
b00110011 0
02
#4517471982
0"
0#
0)
0+
#4561760923
1"
1#
0$
1)
1+
0,
b00110100 0
01
#4606049864
0"
0#
0)
0+
#4650338805
1"
1#
1)
1+
b00110101 0
12
#4694627746
0"
0#
0)
0+
#4738916687
1"
1#
1$
0&
1)
1+
1,
0.
b00110110 0
11
#4783205628
0"
0#
0)
0+
#4827494569
1"
1#
1)
1+
b00110111 0
02
#4871783510
0"
0#
0)
0+
#4916072451
1"
1#
0$
1)
1+
0,
b00111000 0
01
#4960361392
0"
0#
0)
0+
#5004650333
1"
1#
1)
1+
b00111001 0
12
#5048939274
0"
0#
0)
0+
#5093228215
1"
1#
1$
1)
1+
1,
b00111010 0
11
#5137517156
0"
0#
0)
0+
#5181806097
1"
1#
1)
1+
b00111011 0
02
#5226095038
0"
0#
0)
0+
#5270383979
1"
1#
0$
1)
1+
0,
b00111100 0
01
#5314672920
0"
0#
0)
0+
#5358961861
1"
1#
1)
1+
b00111101 0
12
#5403250802
0"
0#
0)
0+
#5447539743
1"
1#
1$
1)
1+
1,
b00111110 0
11
#5491828684
0"
0#
0)
0+
#5536117625
1"
1#
1)
1+
b00111111 0
02
#5580406566
0"
0#
0)
0+
#5624695507
1"
1#
0$
1)
1+
0,
b01000000 0
01
#5668984448
0"
0#
0)
0+
#5713273389
1"
1#
1)
1+
b01000001 0
12
14
#5757562330
0"
0#
0)
0+
#5801851271
1"
1#
1$
1%
1)
1+
1,
1-
b01000010 0
11
13
#5846140212
0"
0#
0)
0+
#5890429153
1"
1#
1)
1+
b01000011 0
02
#5934718094
0"
0#
0)
0+
#5979007035
1"
1#
0$
1)
1+
0,
b01000100 0
01
#6023295976
0"
0#
0)
0+
#6067584917
1"
1#
1)
1+
b01000101 0
12
#6111873858
0"
0#
0)
0+
#6156162799
1"
1#
1$
1&
1)
1+
1,
1.
b01000110 0
11
#6200451740
0"
0#
0)
0+
#6244740681
1"
1#
1)
1+
b01000111 0
02
#6289029622
0"
0#
0)
0+
#6333318563
1"
1#
0$
1)
1+
0,
b01001000 0
01
#6377607504
0"
0#
0)
0+
#6421896445
1"
1#
1)
1+
b01001001 0
12
#6466185386
0"
0#
0)
0+
#6510474327
1"
1#
1$
0&
1)
1+
1,
0.
b01001010 0
11
#6554763268
0"
0#
0)
0+
#6599052209
1"
1#
1)
1+
b01001011 0
02
#6643341150
0"
0#
0)
0+
#6687630091
1"
1#
0$
1)
1+
0,
b01001100 0
01
#6731919032
0"
0#
0)
0+
#6776207973
1"
1#
1)
1+
b01001101 0
12
#6820496914
0"
0#
0)
0+
#6864785855
1"
1#
1$
1&
1)
1+
1,
1.
b01001110 0
11
#6909074796
0"
0#
0)
0+
#6953363737
1"
1#
1)
1+
b01001111 0
02
#6997652678
0"
0#
0)
0+
#7041941619
1"
1#
0$
1)
1+
0,
b01010000 0
01
#7086230560
0"
0#
0)
0+
#7130519501
1"
1#
1)
1+
b01010001 0
12
#7174808442
0"
0#
0)
0+
#7219097383
1"
1#
1$
1)
1+
1,
b01010010 0
11
#7263386324
0"
0#
0)
0+
#7307675265
1"
1#
1)
1+
b01010011 0
02
#7351964206
0"
0#
0)
0+
#7396253147
1"
1#
0$
1)
1+
0,
b01010100 0
01
#7440542088
0"
0#
0)
0+
#7484831029
1"
1#
1)
1+
b01010101 0
12
#7529119970
0"
0#
0)
0+
#7573408911
1"
1#
1$
0&
1)
1+
1,
0.
b01010110 0
11
#7617697852
0"
0#
0)
0+
#7661986793
1"
1#
1)
1+
b01010111 0
02
#7706275734
0"
0#
0)
0+
#7750564675
1"
1#
0$
1)
1+
0,
b01011000 0
01
#7794853616
0"
0#
0)
0+
#7839142557
1"
1#
1)
1+
b01011001 0
12
#7883431498
0"
0#
0)
0+
#7927720439
1"
1#
1$
1)
1+
1,
b01011010 0
11
#7972009380
0"
0#
0)
0+
#8016298321
1"
1#
1)
1+
b01011011 0
02
#8060587262
0"
0#
0)
0+
#8104876203
1"
1#
0$
1)
1+
0,
b01011100 0
01
#8149165144
0"
0#
0)
0+
#8193454085
1"
1#
1)
1+
b01011101 0
12
#8237743026
0"
0#
0)
0+
#8282031967
1"
1#
1$
1)
1+
1,
b01011110 0
11
#8326320908
0"
0#
0)
0+
#8370609849
1"
1#
1)
1+
b01011111 0
02
#8414898790
0"
0#
0)
0+
#8459187731
1"
1#
0$
1)
1+
0,
b01100000 0
01
#8503476672
0"
0#
0)
0+
#8547765613
1"
1#
1)
1+
b01100001 0
12
#8592054554
0"
0#
0)
0+
#8636343495
1"
1#
1$
1)
1+
1,
b01100010 0
11
#8680632436
0"
0#
0)
0+
#8724921377
1"
1#
1)
1+
b01100011 0
02
#8769210318
0"
0#
0)
0+
#8813499259
1"
1#
0$
1)
1+
0,
b01100100 0
01
#8857788200
0"
0#
0)
0+
#8902077141
1"
1#
1)
1+
b01100101 0
12
#8946366082
0"
0#
0)
0+
#8990655023
1"
1#
1$
1&
1)
1+
1,
1.
b01100110 0
11
#9034943964
0"
0#
0)
0+
#9079232905
1"
1#
1)
1+
b01100111 0
02
#9123521846
0"
0#
0)
0+
#9167810787
1"
1#
0$
1)
1+
0,
b01101000 0
01
#9212099728
0"
0#
0)
0+
#9256388669
1"
1#
1)
1+
b01101001 0
12
#9300677610
0"
0#
0)
0+
#9344966551
1"
1#
1$
0&
1)
1+
1,
0.
b01101010 0
11
#9389255492
0"
0#
0)
0+
#9433544433
1"
1#
1)
1+
b01101011 0
02
#9477833374
0"
0#
0)
0+
#9522122315
1"
1#
0$
1)
1+
0,
b01101100 0
01
#9566411256
0"
0#
0)
0+
#9610700197
1"
1#
1)
1+
b01101101 0
12
#9654989138
0"
0#
0)
0+
#9699278079
1"
1#
1$
1&
1)
1+
1,
1.
b01101110 0
11
#9743567020
0"
0#
0)
0+
#9787855961
1"
1#
1)
1+
b01101111 0
02
#9832144902
0"
0#
0)
0+
#9876433843
1"
1#
0$
1)
1+
0,
b01110000 0
01
#9920722784
0"
0#
0)
0+
#9965011725
1"
1#
1)
1+
b01110001 0
12
#10009300666
0"
0#
0)
0+
#10053589607
1"
1#
1$
1)
1+
1,
b01110010 0
11
#10097878548
0"
0#
0)
0+
#10142167489
1"
1#
1)
1+
b01110011 0
02
#10186456430
0"
0#
0)
0+
#10230745371
1"
1#
0$
1)
1+
0,
b01110100 0
01
#10275034312
0"
0#
0)
0+
#10319323253
1"
1#
1)
1+
b01110101 0
12
#10363612194
0"
0#
0)
0+
#10407901135
1"
1#
1$
0&
1)
1+
1,
0.
b01110110 0
11
#10452190076
0"
0#
0)
0+
#10496479017
1"
1#
1)
1+
b01110111 0
02
#10540767958
0"
0#
0)
0+
#10585056899
1"
1#
0$
1)
1+
0,
b01111000 0
01
#10629345840
0"
0#
0)
0+
#10673634781
1"
1#
1)
1+
b01111001 0
12
#10717923722
0"
0#
0)
0+
#10762212663
1"
1#
1$
1)
1+
1,
b01111010 0
11
#10806501604
0"
0#
0)
0+
#10850790545
1"
1#
1)
1+
b01111011 0
02
#10895079486
0"
0#
0)
0+
#10939368427
1"
1#
0$
1)
1+
0,
b01111100 0
01
#10983657368
0"
0#
0)
0+
#11027946309
1"
1#
1)
1+
b01111101 0
12
#11072235250
0"
0#
0)
0+
#11116524191
1"
1#
1$
1)
1+
1,
b01111110 0
11
#11160813132
0"
0#
0)
0+
#11205102073
1"
1#
1)
1+
b01111111 0
02
#11249391014
0"
0#
0)
0+
#11293679955
1"
1#
0$
1)
1+
0,
b10000000 0
01
#11337968896
0"
0#
0)
0+
#11382257837
1"
1#
1)
1+
b10000001 0
12
04
#11426546778
0"
0#
0)
0+
#11470835719
1"
1#
1$
0%
1)
1+
1,
0-
b10000010 0
11
03
#11515124660
0"
0#
0)
0+
#11559413601
1"
1#
1)
1+
b10000011 0
02
#11603702542
0"
0#
0)
0+
#11647991483
1"
1#
0$
1)
1+
0,
b10000100 0
01
#11692280424
0"
0#
0)
0+
#11736569365
1"
1#
1)
1+
b10000101 0
12
#11780858306
0"
0#
0)
0+
#11825147247
1"
1#
1$
1&
1)
1+
1,
1.
b10000110 0
11
#11869436188
0"
0#
0)
0+
#11913725129
1"
1#
1)
1+
b10000111 0
02
#11958014070
0"
0#
0)
0+
#12002303011
1"
1#
0$
1)
1+
0,
b10001000 0
01
#12046591952
0"
0#
0)
0+
#12090880893
1"
1#
1)
1+
b10001001 0
12
#12135169834
0"
0#
0)
0+
#12179458775
1"
1#
1$
0&
1)
1+
1,
0.
b1 /
b10001010 0
11
b0000000000000001 5
#12223747716
0"
0#
0)
0+
#12268036657
1"
1#
1)
1+
b10001011 0
02
#12312325598
0"
0#
0)
0+
#12356614539
1"
1#
0$
1)
1+
0,
b10001100 0
01
#12400903480
0"
0#
0)
0+
#12445192421
1"
1#
1)
1+
b10001101 0
12
#12489481362
0"
0#
0)
0+
#12533770303
1"
1#
1$
1&
1)
1+
1,
1.
b10 /
b10001110 0
11
b0000000000000010 5
#12578059244
0"
0#
0)
0+
#12622348185
1"
1#
1)
1+
b10001111 0
02
#12666637126
0"
0#
0)
0+
#12710926067
1"
1#
0$
1)
1+
0,
b10010000 0
01
#12755215008
0"
0#
0)
0+
#12799503949
1"
1#
1)
1+
b10010001 0
12
#12843792890
0"
0#
0)
0+
#12888081831
1"
1#
1$
1)
1+
1,
b11 /
b10010010 0
11
b0000000000000101 5
#12932370772
0"
0#
0)
0+
#12976659713
1"
1#
1)
1+
b10010011 0
02
#13020948654
0"
0#
0)
0+
#13065237595
1"
1#
0$
1)
1+
0,
b10010100 0
01
#13109526536
0"
0#
0)
0+
#13153815477
1"
1#
1)
1+
b10010101 0
12
#13198104418
0"
0#
0)
0+
#13242393359
1"
1#
1$
0&
1)
1+
1,
0.
b100 /
b10010110 0
11
b0000000000001011 5
#13286682300
0"
0#
0)
0+
#13330971241
1"
1#
1)
1+
b10010111 0
02
#13375260182
0"
0#
0)
0+
#13419549123
1"
1#
0$
1)
1+
0,
b10011000 0
01
#13463838064
0"
0#
0)
0+
#13508127005
1"
1#
1)
1+
b10011001 0
12
#13552415946
0"
0#
0)
0+
#13596704887
1"
1#
1$
1)
1+
1,
b101 /
b10011010 0
11
b0000000000010110 5
#13640993828
0"
0#
0)
0+
#13685282769
1"
1#
1)
1+
b10011011 0
02
#13729571710
0"
0#
0)
0+
#13773860651
1"
1#
0$
1)
1+
0,
b10011100 0
01
#13818149592
0"
0#
0)
0+
#13862438533
1"
1#
1)
1+
b10011101 0
12
#13906727474
0"
0#
0)
0+
#13951016415
1"
1#
1$
1)
1+
1,
b110 /
b10011110 0
11
b0000000000101100 5
#13995305356
0"
0#
0)
0+
#14039594297
1"
1#
1)
1+
b10011111 0
02
#14083883238
0"
0#
0)
0+
#14128172179
1"
1#
0$
1)
1+
0,
b10100000 0
01
#14172461120
0"
0#
0)
0+
#14216750061
1"
1#
1)
1+
b10100001 0
12
#14261039002
0"
0#
0)
0+
#14305327943
1"
1#
1$
1)
1+
1,
b111 /
b10100010 0
11
b0000000001011000 5
#14349616884
0"
0#
0)
0+
#14393905825
1"
1#
1)
1+
b10100011 0
02
#14438194766
0"
0#
0)
0+
#14482483707
1"
1#
0$
1)
1+
0,
b10100100 0
01
#14526772648
0"
0#
0)
0+
#14571061589
1"
1#
1)
1+
b10100101 0
12
#14615350530
0"
0#
0)
0+
#14659639471
1"
1#
1$
1&
1)
1+
1,
1.
b1000 /
b10100110 0
11
b0000000010110000 5
#14703928412
0"
0#
0)
0+
#14748217353
1"
1#
1)
1+
b10100111 0
02
#14792506294
0"
0#
0)
0+
#14836795235
1"
1#
0$
1)
1+
0,
b10101000 0
01
#14881084176
0"
0#
0)
0+
#14925373117
1"
1#
1)
1+
b10101001 0
12
#14969662058
0"
0#
0)
0+
#15013950999
1"
1#
1$
0&
1)
1+
1,
0.
b1001 /
b10101010 0
11
b0000000101100001 5
#15058239940
0"
0#
0)
0+
#15102528881
1"
1#
1)
1+
b10101011 0
02
#15146817822
0"
0#
0)
0+
#15191106763
1"
1#
0$
1)
1+
0,
b10101100 0
01
#15235395704
0"
0#
0)
0+
#15279684645
1"
1#
1)
1+
b10101101 0
12
#15323973586
0"
0#
0)
0+
#15368262527
1"
1#
1$
1&
1)
1+
1,
1.
b1010 /
b10101110 0
11
b0000001011000010 5
#15412551468
0"
0#
0)
0+
#15456840409
1"
1#
1)
1+
b10101111 0
02
#15501129350
0"
0#
0)
0+
#15545418291
1"
1#
0$
1)
1+
0,
b10110000 0
01
#15589707232
0"
0#
0)
0+
#15633996173
1"
1#
1)
1+
b10110001 0
12
#15678285114
0"
0#
0)
0+
#15722574055
1"
1#
1$
1)
1+
1,
b1011 /
b10110010 0
11
b0000010110000101 5
#15766862996
0"
0#
0)
0+
#15811151937
1"
1#
1)
1+
b10110011 0
02
#15855440878
0"
0#
0)
0+
#15899729819
1"
1#
0$
1)
1+
0,
b10110100 0
01
#15944018760
0"
0#
0)
0+
#15988307701
1"
1#
1)
1+
b10110101 0
12
#16032596642
0"
0#
0)
0+
#16076885583
1"
1#
1$
0&
1)
1+
1,
0.
b1100 /
b10110110 0
11
b0000101100001011 5
#16121174524
0"
0#
0)
0+
#16165463465
1"
1#
1)
1+
b10110111 0
02
#16209752406
0"
0#
0)
0+
#16254041347
1"
1#
0$
1)
1+
0,
b10111000 0
01
#16298330288
0"
0#
0)
0+
#16342619229
1"
1#
1)
1+
b10111001 0
12
#16386908170
0"
0#
0)
0+
#16431197111
1"
1#
1$
1)
1+
1,
b1101 /
b10111010 0
11
b0001011000010110 5
#16475486052
0"
0#
0)
0+
#16519774993
1"
1#
1)
1+
b10111011 0
02
#16564063934
0"
0#
0)
0+
#16608352875
1"
1#
0$
1)
1+
0,
b10111100 0
01
#16652641816
0"
0#
0)
0+
#16696930757
1"
1#
1)
1+
b10111101 0
12
#16741219698
0"
0#
0)
0+
#16785508639
1"
1#
1$
1)
1+
1,
b1110 /
b10111110 0
11
b0010110000101100 5
#16829797580
0"
0#
0)
0+
#16874086521
1"
1#
1)
1+
b10111111 0
02
#16918375462
0"
0#
0)
0+
#16962664403
1"
1#
0$
1)
1+
0,
b11000000 0
01
#17006953344
0"
0#
0)
0+
#17051242285
1"
1#
1)
1+
b11000001 0
12
14
#17095531226
0"
0#
0)
0+
#17139820167
1"
1#
1$
1%
1)
1+
1,
1-
b1111 /
b11000010 0
11
13
b0101100001011000 5
#17184109108
0"
0#
0)
0+
#17228398049
1"
1#
1)
1+
b11000011 0
02
#17272686990
0"
0#
0)
0+
#17316975931
1"
1#
0$
1)
1+
0,
b11000100 0
01
#17361264872
0"
0#
0)
0+
#17405553813
1"
1#
1)
1+
b11000101 0
12
#17449842754
0"
0#
0)
0+
#17494131695
1"
1#
1$
1&
1)
1+
1,
1.
b10000 /
b11000110 0
11
b1011000010110000 5
#17538420636
0"
0#
0)
0+
#17582709577
1"
1#
1)
1+
b0 /
b11000111 0
02
#17626998518
0"
0#
0)
0+
#17671287459
1"
1#
0$
b1011000010110000 '
1)
b1011000010110000 *
1+
0,
b11001000 0
01
#17715576400
0"
0#
0)
0+
#17759865341
1"
1#
1)
1+
b11001001 0
12
#17804154282
0"
0#
0)
0+
#17848443223
1"
1#
1$
0&
1)
1+
1,
0.
b11001010 0
11
#17892732164
0"
0#
0)
0+
#17937021105
1"
1#
1)
1+
b11001011 0
02
b0000000000000000 5
#17981310046
0"
0#
0)
0+
#18025598987
1"
1#
0$
1)
1+
0,
b11001100 0
01
#18069887928
0"
0#
0)
0+
#18114176869
1"
1#
1)
1+
b11001101 0
12
#18158465810
0"
0#
0)
0+
#18202754751
1"
1#
1$
1&
1)
1+
1,
1.
b11001110 0
11
#18247043692
0"
0#
0)
0+
#18291332633
1"
1#
1)
1+
b11001111 0
02
#18335621574
0"
0#
0)
0+
#18379910515
1"
1#
0$
1)
1+
0,
b11010000 0
01
#18424199456
0"
0#
0)
0+
#18468488397
1"
1#
1)
1+
b11010001 0
12
#18512777338
0"
0#
0)
0+
#18557066279
1"
1#
1$
1)
1+
1,
b11010010 0
11
#18601355220
0"
0#
0)
0+
#18645644161
1"
1#
1)
1+
b11010011 0
02
#18689933102
0"
0#
0)
0+
#18734222043
1"
1#
0$
1)
1+
0,
b11010100 0
01
#18778510984
0"
0#
0)
0+
#18822799925
1"
1#
1)
1+
b11010101 0
12
#18867088866
0"
0#
0)
0+
#18911377807
1"
1#
1$
0&
1)
1+
1,
0.
b11010110 0
11
#18955666748
0"
0#
0)
0+
#18999955689
1"
1#
1)
1+
b11010111 0
02
#19044244630
0"
0#
0)
0+
#19088533571
1"
1#
0$
1)
1+
0,
b11011000 0
01
#19132822512
0"
0#
0)
0+
#19177111453
1"
1#
1)
1+
b11011001 0
12
#19221400394
0"
0#
0)
0+
#19265689335
1"
1#
1$
1)
1+
1,
b11011010 0
11
#19309978276
0"
0#
0)
0+
#19354267217
1"
1#
1)
1+
b11011011 0
02
#19398556158
0"
0#
0)
0+
#19442845099
1"
1#
0$
1)
1+
0,
b11011100 0
01
#19487134040
0"
0#
0)
0+
#19531422981
1"
1#
1)
1+
b11011101 0
12
#19575711922
0"
0#
0)
0+
#19620000863
1"
1#
1$
1)
1+
1,
b11011110 0
11
#19664289804
0"
0#
0)
0+
#19708578745
1"
1#
1)
1+
b11011111 0
02
#19752867686
0"
0#
0)
0+
#19797156627
1"
1#
0$
1)
1+
0,
b11100000 0
01
#19841445568
0"
0#
0)
0+
#19885734509
1"
1#
1)
1+
b11100001 0
12
#19930023450
0"
0#
0)
0+
#19974312391
1"
1#
1$
1)
1+
1,
b11100010 0
11
#20018601332
0"
0#
0)
0+
#20062890273
1"
1#
1)
1+
b11100011 0
02
#20107179214
0"
0#
0)
0+
#20151468155
1"
1#
0$
1)
1+
0,
b11100100 0
01
#20195757096
0"
0#
0)
0+
#20240046037
1"
1#
1)
1+
b11100101 0
12
#20284334978
0"
0#
0)
0+
#20328623919
1"
1#
1$
1&
1)
1+
1,
1.
b11100110 0
11
#20372912860
0"
0#
0)
0+
#20417201801
1"
1#
1)
1+
b11100111 0
02
#20461490742
0"
0#
0)
0+
#20505779683
1"
1#
0$
1)
1+
0,
b11101000 0
01
#20550068624
0"
0#
0)
0+
#20594357565
1"
1#
1)
1+
b11101001 0
12
#20638646506
0"
0#
0)
0+
#20682935447
1"
1#
1$
0&
1)
1+
1,
0.
b11101010 0
11
#20727224388
0"
0#
0)
0+
#20771513329
1"
1#
1)
1+
b11101011 0
02
#20815802270
0"
0#
0)
0+
#20860091211
1"
1#
0$
1)
1+
0,
b11101100 0
01
#20904380152
0"
0#
0)
0+
#20948669093
1"
1#
1)
1+
b11101101 0
12
#20992958034
0"
0#
0)
0+
#21037246975
1"
1#
1$
1&
1)
1+
1,
1.
b11101110 0
11
#21081535916
0"
0#
0)
0+
#21125824857
1"
1#
1)
1+
b11101111 0
02
#21170113798
0"
0#
0)
0+
#21214402739
1"
1#
0$
1)
1+
0,
b11110000 0
01
#21258691680
0"
0#
0)
0+
#21302980621
1"
1#
1)
1+
b11110001 0
12
#21347269562
0"
0#
0)
0+
#21391558503
1"
1#
1$
1)
1+
1,
b11110010 0
11
#21435847444
0"
0#
0)
0+
#21480136385
1"
1#
1)
1+
b11110011 0
02
#21524425326
0"
0#
0)
0+
#21568714267
1"
1#
0$
1)
1+
0,
b11110100 0
01
#21613003208
0"
0#
0)
0+
#21657292149
1"
1#
1)
1+
b11110101 0
12
#21701581090
0"
0#
0)
0+
#21745870031
1"
1#
1$
0&
1)
1+
1,
0.
b11110110 0
11
#21790158972
0"
0#
0)
0+
#21834447913
1"
1#
1)
1+
b11110111 0
02
#21878736854
0"
0#
0)
0+
#21923025795
1"
1#
0$
1)
1+
0,
b11111000 0
01
#21967314736
0"
0#
0)
0+
#22011603677
1"
1#
1)
1+
b11111001 0
12
#22055892618
0"
0#
0)
0+
#22100181559
1"
1#
1$
1)
1+
1,
b11111010 0
11
#22144470500
0"
0#
0)
0+
