i2s/i2s_loop/synth/axi_i2s_writer.vhd
-- mclk/sclk = 4
-- mclk/lrck = 128
-- sclk/lrck = 32

library ieee;
use ieee.std_logic_1164.all;
use ieee.numeric_std.all;

entity axi_i2s_writer is

  generic(
    DATA_LENGTH : INTEGER := 16
  );

	port(
    -- SYSTEM
		resetn  :	in	std_logic;
		clk	    :	in	std_logic;

    -- AXI
		tvalid	: in  std_logic;
    tlast		: in  std_logic;
		tdata		:	in  std_logic_vector((DATA_LENGTH-1) downto 0);
    tready	: out std_logic;

    -- I2S
		mclk    :	out	std_logic;
		sclk	  :	out std_logic;
		lrck	  :	out std_logic;
		dout    :	out std_logic
	);
end entity axi_i2s_writer;

architecture arch of axi_i2s_writer is

  signal cpt_clk		:	unsigned (6 downto 0);
  signal sclk_old   : std_logic;
  signal sclk_cur   : std_logic;
  signal reg_dec    : std_logic_vector(DATA_LENGTH-1 downto 0);
  signal cpt_dout   : integer;  -- compte les bits ecrits sur dout
  signal reg_tready : std_logic;
  signal reg_tvalid : std_logic;

begin

  process(clk, resetn) is

    begin

    if (resetn = '0') then
      cpt_clk    <= (others => '0');
      sclk_old   <= '0';
      sclk_cur   <= '0';
      reg_dec    <= (others => '0');
      cpt_dout   <= 0;
      reg_tready <= '0';
      reg_tvalid <= '0';

    elsif (rising_edge(clk)) then
      cpt_clk  <= cpt_clk + 1;
      sclk_old <= sclk_cur;
      sclk_cur <= cpt_clk(1);

      if (reg_tready = '1') then
        reg_tready <= '0';
      else end if;

      if (tvalid = '1') then
        reg_tvalid <= '1';
      else end if;

      -- detection front montant sclk
      if (sclk_old = '0' and sclk_cur = '1') then
        -- nouvelle donnée
          if (reg_tvalid = '1' and cpt_dout = 0) then
            reg_dec    <= tdata;
            reg_tready <= '0';
            cpt_dout   <= 1;
            reg_tvalid <= '0';
          -- lecture 1 ; 14
        elsif (cpt_dout > 0 and cpt_dout < DATA_LENGTH - 1) then
            reg_dec    <= reg_dec(reg_dec'length-2 downto 0) & '0';
            cpt_dout   <= cpt_dout + 1;
          -- dernière lecture (cpt_data = 15)
          else
            reg_dec    <= reg_dec(reg_dec'length-2 downto 0) & '0';
            cpt_dout   <= 0;
            reg_tready <= '1';
          end if;
      else end if;
    end if;

  end process;

  mclk   <= clk;
  sclk   <= cpt_clk(1);
  lrck   <= cpt_clk(6);
  tready <= reg_tready;
  dout   <= reg_dec(reg_dec'length - 1);

end architecture arch;

i2s/i2s_loop/synth/axi_i2s_reader.vhd
-- I2S Reader en mode esclave + receiver
-- Lit la sortie de l'ADC et la formatte sur DATA_LENGTH bits en sortie

-- mclk/sclk = 4
-- mclk/lrck = 256

library ieee;
use ieee.std_logic_1164.all;
use ieee.numeric_std.all;

entity axi_i2s_reader is

  generic(
    DATA_LENGTH : INTEGER := 16
  );

	port(
		resetn  :	in	std_logic;		-- fourni par le systeme
		clk	    :	in	std_logic;		-- fourni par le systeme
		data	  :	out	std_logic_vector((DATA_LENGTH-1) downto 0);

    -- AXI
		tready	: in  std_logic;   -- on ignore ici
		tvalid	: out std_logic;   -- 1 quand on update une donnée, 0 sinon
		tlast		: out std_logic;   -- 1 tous les 2048 envois
		tdata		:	out	std_logic_vector((DATA_LENGTH-1) downto 0);

		mclk    :	out	std_logic;		-- clock du systeme
		sclk	  :	out std_logic;		-- bit clock : frequence de din
		lrck	  :	out std_logic;		-- left / right : change tout les (DATA_LENGTH+2) * SCLK
		din	    :	in 	std_logic		  -- sortie de l'ADC
	);
end entity axi_i2s_reader;

architecture arch of axi_i2s_reader is

  signal cpt_clk		:	unsigned (7 downto 0);
  signal cpt_din    : integer;  -- nombre de din reçu
  signal cpt_data   : integer;  -- nombre de données envoyées
  signal sclk_old   : std_logic;
  signal sclk_cur   : std_logic;
  signal reg_dec    : std_logic_vector(DATA_LENGTH-1 downto 0);
  signal reg_tvalid : std_logic;

begin

  process(clk, resetn) is

    begin

    if (resetn = '0') then
      cpt_clk    <= (others => '0');
      cpt_din    <= 0;
      cpt_data   <= 0;
      sclk_old   <= '0';
      sclk_cur   <= '0';

      reg_dec    <= (others => '0');
      reg_tvalid <= '0';
      tdata      <= (others => '0');
      tlast      <= '0';

    elsif (rising_edge(clk)) then
      cpt_clk  <= cpt_clk + 1;
      sclk_old <= sclk_cur;
      sclk_cur <= cpt_clk(1);

      if (reg_tvalid = '1') then
        reg_tvalid <= '0';
      else end if;

      -- detection front montant sclk
      if (sclk_old = '0' and sclk_cur = '1') then

        -- on attend un coup de clock avant MSB
        cpt_din <= cpt_din + 1;

        if (cpt_din >= 1 and cpt_din <= DATA_LENGTH) then
          -- on remplit de droite à gauche
          reg_dec <= reg_dec(reg_dec'length-2 downto 0) & din;

        -- donnée prête
        elsif (cpt_din >= DATA_LENGTH + 1) then
          cpt_din    <= 0;
          tdata      <= reg_dec;
          reg_tvalid <= '1';
          reg_dec    <= (others => '0');

          if (cpt_data < 2048) then
            cpt_data <= cpt_data + 1;
            tlast    <= '0';
          elsif (cpt_data >= 2048) then
            cpt_data <= 0;
            tlast    <= '1';
          else end if;
        else end if;
      else end if;
    end if;

  end process;

  mclk   <= clk;
  sclk   <= cpt_clk(1);
  lrck   <= cpt_clk(7);
  tvalid <= reg_tvalid;

end architecture arch;

i2s/i2s_loop/synth/i2s_loop.vhd
library ieee;
use ieee.std_logic_1164.all;
use ieee.numeric_std.all;

entity i2s_loop is

  generic (
      DATA_LENGTH : integer := 16
  );

  port (
      resetn : in std_logic;
      clk    : in std_logic;

      -- PMOD OUT : entrée de l'i2s reader
      mclko  : out std_logic;
      sclko  : out std_logic;
      lrcko  : out std_logic;
      din    : in  std_logic;

      -- PMOD IN : sortie de l'i2s writer
      mclki  : out std_logic;
      sclki  : out std_logic;
      lrcki  : out std_logic;
      dout   : out std_logic
  );

end entity;

architecture arch of i2s_loop is

  signal tvalid, tready, tlast : std_logic;
  signal tdata : std_logic_vector(DATA_LENGTH-1 downto 0);

begin

    i2s_reader : entity work.axi_i2s_reader
    generic map (
        DATA_LENGTH=>DATA_LENGTH
    )
    port map (
        resetn=>resetn, clk=>clk,
        mclk=>mclko, sclk=>sclko, lrck=>lrcko, din=>din,
        tvalid=>tvalid, tready=>tready, tlast=>tlast,
        tdata=>tdata
    );

    i2s_writer : entity work.axi_i2s_writer
    generic map (
        DATA_LENGTH=>DATA_LENGTH
    )
    port map (
        resetn=>resetn, clk=>clk,
        mclk=>mclki, sclk=>sclki, lrck=>lrcki, dout=>dout,
        tvalid=>tvalid, tready=>tready, tlast=>tlast,
        tdata=>tdata
    );

end architecture;

i2s/i2s_loop/sim/i2s_loop_tb.vhd
library ieee;
use ieee.std_logic_1164.all;
use ieee.numeric_std.all;

entity i2s_loop_tb is

end entity;

architecture arch of i2s_loop_tb is

  constant clock_t : time :=  44.288941 ns;

  signal clk, resetn               : std_logic;
  signal mclki, sclki, lrcki, din  : std_logic;
  signal mclko, sclko, lrcko, dout : std_logic;
  signal cpt : integer := 0;

begin

  axi_i2s_loop : entity work.i2s_loop port map (
      resetn=>resetn, clk=>clk,
      mclko=>mclko, sclko=>sclko, lrcko=>lrcko, din=>din,
      mclki=>mclki, sclki=>sclki, lrcki=>lrcki, dout=>dout
  );

  clock : process begin
      clk <= '0';
      wait for clock_t;
      clk <= '1';
      wait for clock_t;
  end process clock;

  rst_p : process begin
      resetn <= '0';
      wait for clock_t;
      resetn <= '1';
      wait for 50 us;
      wait;
  end process;

  data_p : process(resetn, sclki)
  begin

      if rising_edge(sclki) then
          if (cpt = 0) then
            din <= '1';
            cpt <= cpt + 1;
          elsif (cpt = 1) then
            din <= '1';
            cpt <= cpt + 1;
          elsif (cpt = 2) then
            din <= '0';
            cpt <= 0;
          else end if;
      else end if;
end process;


end architecture;

i2s/i2s_loop/i2s_loop_tb.vcd
$date
  Tue Dec 15 12:15:58 2020
$end
$version
  GHDL v0
$end
$timescale
  1 fs
$end
$scope module standard $end
$upscope $end
$scope module std_logic_1164 $end
$upscope $end
$scope module numeric_std $end
$upscope $end
$scope module i2s_loop_tb $end
$var reg 1 ! clk $end
$var reg 1 " resetn $end
$var reg 1 # mclki $end
$var reg 1 $ sclki $end
$var reg 1 % lrcki $end
$var reg 1 & din $end
$var reg 1 ' mclko $end
$var reg 1 ( sclko $end
$var reg 1 ) lrcko $end
$var reg 1 * dout $end
$var integer 32 + cpt $end
$scope module axi_i2s_loop $end
$var reg 1 , resetn $end
$var reg 1 - clk $end
$var reg 1 . mclko $end
$var reg 1 / sclko $end
$var reg 1 0 lrcko $end
$var reg 1 1 din $end
$var reg 1 2 mclki $end
$var reg 1 3 sclki $end
$var reg 1 4 lrcki $end
$var reg 1 5 dout $end
$var reg 1 6 tvalid $end
$var reg 1 7 tready $end
$var reg 1 8 tlast $end
$var reg 16 9 tdata[15:0] $end
$scope module i2s_reader $end
$var reg 1 : resetn $end
$var reg 1 ; clk $end
$var reg 16 < data[15:0] $end
$var reg 1 = tready $end
$var reg 1 > tvalid $end
$var reg 1 ? tlast $end
$var reg 16 @ tdata[15:0] $end
$var reg 1 A mclk $end
$var reg 1 B sclk $end
$var reg 1 C lrck $end
$var reg 1 D din $end
$var reg 8 E cpt_clk[7:0] $end
$var integer 32 F cpt_din $end
$var integer 32 G cpt_data $end
$var reg 1 H sclk_old $end
$var reg 1 I sclk_cur $end
$var reg 16 J reg_dec[15:0] $end
$var reg 1 K reg_tvalid $end
$upscope $end
$scope module i2s_writer $end
$var reg 1 L resetn $end
$var reg 1 M clk $end
$var reg 1 N tvalid $end
$var reg 1 O tlast $end
$var reg 16 P tdata[15:0] $end
$var reg 1 Q tready $end
$var reg 1 R mclk $end
$var reg 1 S sclk $end
$var reg 1 T lrck $end
$var reg 1 U dout $end
$var reg 7 V cpt_clk[6:0] $end
$var reg 1 W sclk_old $end
$var reg 1 X sclk_cur $end
$var reg 16 Y reg_dec[15:0] $end
$var integer 32 Z cpt_dout $end
$var reg 1 [ reg_tready $end
$var reg 1 \ reg_tvalid $end
$upscope $end
$upscope $end
$upscope $end
$enddefinitions $end
#0
0!
0"
0#
0$
0%
U&
0'
0(
0)
0*
b0 +
0,
0-
0.
0/
00
U1
02
03
04
05
06
07
08
b0000000000000000 9
0:
0;
bUUUUUUUUUUUUUUUU <
0=
0>
0?
b0000000000000000 @
0A
0B
0C
UD
b00000000 E
b0 F
b0 G
0H
0I
b0000000000000000 J
0K
0L
0M
0N
0O
b0000000000000000 P
0Q
0R
0S
0T
0U
b0000000 V
0W
0X
b0000000000000000 Y
b0 Z
0[
0\
#44288941
1!
1"
1#
1'
1,
1-
1.
12
1:
1;
1A
b00000001 E
1L
1M
1R
b0000001 V
#88577882
0!
0#
0'
0-
0.
02
0;
0A
0M
0R
#132866823
1!
1#
1$
1&
1'
1(
b1 +
1-
1.
1/
11
12
13
1;
1A
1B
1D
b00000010 E
1M
1R
1S
b0000010 V
#177155764
0!
0#
0'
0-
0.
02
0;
0A
0M
0R
#221444705
1!
1#
1'
1-
1.
12
1;
1A
b00000011 E
1I
1M
1R
b0000011 V
1X
#265733646
0!
0#
0'
0-
0.
02
0;
0A
0M
0R
#310022587
1!
1#
0$
1'
0(
1-
1.
0/
12
03
17
1;
1=
1A
0B
b00000100 E
b1 F
1H
1M
1Q
1R
0S
b0000100 V
1W
1[
#354311528
0!
0#
0'
0-
0.
02
0;
0A
0M
0R
#398600469
1!
1#
1'
1-
1.
12
07
1;
0=
1A
b00000101 E
0I
1M
0Q
1R
b0000101 V
0X
0[
#442889410
0!
0#
0'
0-
0.
02
0;
0A
0M
0R
#487178351
1!
1#
1$
1'
1(
b10 +
1-
1.
1/
12
13
1;
1A
1B
b00000110 E
0H
1M
1R
1S
b0000110 V
0W
#531467292
0!
0#
0'
0-
0.
02
0;
0A
0M
0R
#575756233
1!
1#
1'
1-
1.
12
1;
1A
b00000111 E
1I
1M
1R
b0000111 V
1X
#620045174
0!
0#
0'
0-
0.
02
0;
0A
0M
0R
#664334115
1!
1#
0$
1'
0(
1-
1.
0/
12
03
17
1;
1=
1A
0B
b00001000 E
b10 F
1H
b0000000000000001 J
1M
1Q
1R
0S
b0001000 V
1W
1[
#708623056
0!
0#
0'
0-
0.
02
0;
0A
0M
0R
#752911997
1!
1#
1'
1-
1.
12
07
1;
0=
1A
b00001001 E
0I
1M
0Q
1R
b0001001 V
0X
0[
#797200938
0!
0#
0'
0-
0.
02
0;
0A
0M
0R
#841489879
1!
1#
1$
0&
1'
1(
b0 +
1-
1.
1/
01
12
13
1;
1A
1B
0D
b00001010 E
0H
1M
1R
1S
b0001010 V
0W
#885778820
0!
0#
0'
0-
0.
02
0;
0A
0M
0R
#930067761
1!
1#
1'
1-
1.
12
1;
1A
b00001011 E
1I
1M
1R
b0001011 V
1X
#974356702
0!
0#
0'
0-
0.
02
0;
0A
0M
0R
#1018645643
1!
1#
0$
1'
0(
1-
1.
0/
12
03
17
1;
1=
1A
0B
b00001100 E
b11 F
1H
b0000000000000010 J
1M
1Q
1R
0S
b0001100 V
1W
1[
#1062934584
0!
0#
0'
0-
0.
02
0;
0A
0M
0R
#1107223525
1!
1#
1'
1-
1.
12
07
1;
0=
1A
b00001101 E
0I
1M
0Q
1R
b0001101 V
0X
0[
#1151512466
0!
0#
0'
0-
0.
02
0;
0A
0M
0R
#1195801407
1!
1#
1$
1&
1'
1(
b1 +
1-
1.
1/
11
12
13
1;
1A
1B
1D
b00001110 E
0H
1M
1R
1S
b0001110 V
0W
#1240090348
0!
0#
0'
0-
0.
02
0;
0A
0M
0R
#1284379289
1!
1#
1'
1-
1.
12
1;
1A
b00001111 E
1I
1M
1R
b0001111 V
1X
#1328668230
0!
0#
0'
0-
0.
02
0;
0A
0M
0R
#1372957171
1!
1#
0$
1'
0(
1-
1.
0/
12
03
17
1;
1=
1A
0B
b00010000 E
b100 F
1H
b0000000000000101 J
1M
1Q
1R
0S
b0010000 V
1W
1[
#1417246112
0!
0#
0'
0-
0.
02
0;
0A
0M
0R
#1461535053
1!
1#
1'
1-
1.
12
07
1;
0=
1A
b00010001 E
0I
1M
0Q
1R
b0010001 V
0X
0[
#1505823994
0!
0#
0'
0-
0.
02
0;
0A
0M
0R
#1550112935
1!
1#
1$
1'
1(
b10 +
1-
1.
1/
12
13
1;
1A
1B
b00010010 E
0H
1M
1R
1S
b0010010 V
0W
#1594401876
0!
0#
0'
0-
0.
02
0;
0A
0M
0R
#1638690817
1!
1#
1'
1-
1.
12
1;
1A
b00010011 E
1I
1M
1R
b0010011 V
1X
#1682979758
0!
0#
0'
0-
0.
02
0;
0A
0M
0R
#1727268699
1!
1#
0$
1'
0(
1-
1.
0/
12
03
17
1;
1=
1A
0B
b00010100 E
b101 F
1H
b0000000000001011 J
1M
1Q
1R
0S
b0010100 V
1W
1[
#1771557640
0!
0#
0'
0-
0.
02
0;
0A
0M
0R
#1815846581
1!
1#
1'
1-
1.
12
07
1;
0=
1A
b00010101 E
0I
1M
0Q
1R
b0010101 V
0X
0[
#1860135522
0!
0#
0'
0-
0.
02
0;
0A
0M
0R
#1904424463
1!
1#
1$
0&
1'
1(
b0 +
1-
1.
1/
01
12
13
1;
1A
1B
0D
b00010110 E
0H
1M
1R
1S
b0010110 V
0W
#1948713404
0!
0#
0'
0-
0.
02
0;
0A
0M
0R
#1993002345
1!
1#
1'
1-
1.
12
1;
1A
b00010111 E
1I
1M
1R
b0010111 V
1X
#2037291286
0!
0#
0'
0-
0.
02
0;
0A
0M
0R
#2081580227
1!
1#
0$
1'
0(
1-
1.
0/
12
03
17
1;
1=
1A
0B
b00011000 E
b110 F
1H
b0000000000010110 J
1M
1Q
1R
0S
b0011000 V
1W
1[
#2125869168
0!
0#
0'
0-
0.
02
0;
0A
0M
0R
#2170158109
1!
1#
1'
1-
1.
12
07
1;
0=
1A
b00011001 E
0I
1M
0Q
1R
b0011001 V
0X
0[
#2214447050
0!
0#
0'
0-
0.
02
0;
0A
0M
0R
#2258735991
1!
1#
1$
1&
1'
1(
b1 +
1-
1.
1/
11
12
13
1;
1A
1B
1D
b00011010 E
0H
1M
1R
1S
b0011010 V
0W
#2303024932
0!
0#
0'
0-
0.
02
0;
0A
0M
0R
#2347313873
1!
1#
1'
1-
1.
12
1;
1A
b00011011 E
1I
1M
1R
b0011011 V
1X
#2391602814
0!
0#
0'
0-
0.
02
0;
0A
0M
0R
#2435891755
1!
1#
0$
1'
0(
1-
1.
0/
12
03
17
1;
1=
1A
0B
b00011100 E
b111 F
1H
b0000000000101101 J
1M
1Q
1R
0S
b0011100 V
1W
1[
#2480180696
0!
0#
0'
0-
0.
02
0;
0A
0M
0R
#2524469637
1!
1#
1'
1-
1.
12
07
1;
0=
1A
b00011101 E
0I
1M
0Q
1R
b0011101 V
0X
0[
#2568758578
0!
0#
0'
0-
0.
02
0;
0A
0M
0R
#2613047519
1!
1#
1$
1'
1(
b10 +
1-
1.
1/
12
13
1;
1A
1B
b00011110 E
0H
1M
1R
1S
b0011110 V
0W
#2657336460
0!
0#
0'
0-
0.
02
0;
0A
0M
0R
#2701625401
1!
1#
1'
1-
1.
12
1;
1A
b00011111 E
1I
1M
1R
b0011111 V
1X
#2745914342
0!
0#
0'
0-
0.
02
0;
0A
0M
0R
#2790203283
1!
1#
0$
1'
0(
1-
1.
0/
12
03
17
1;
1=
1A
0B
b00100000 E
b1000 F
1H
b0000000001011011 J
1M
1Q
1R
0S
b0100000 V
1W
1[
#2834492224
0!
0#
0'
0-
0.
02
0;
0A
0M
0R
#2878781165
1!
1#
1'
1-
1.
12
07
1;
0=
1A
b00100001 E
0I
1M
0Q
1R
b0100001 V
0X
0[
#2923070106
0!
0#
0'
0-
0.
02
0;
0A
0M
0R
#2967359047
1!
1#
1$
0&
1'
1(
b0 +
1-
1.
1/
01
12
13
1;
1A
1B
0D
b00100010 E
0H
1M
1R
1S
b0100010 V
0W
#3011647988
0!
0#
0'
0-
0.
02
0;
0A
0M
0R
#3055936929
1!
1#
1'
1-
1.
12
1;
1A
b00100011 E
1I
1M
1R
b0100011 V
1X
#3100225870
0!
0#
0'
0-
0.
02
0;
0A
0M
0R
#3144514811
1!
1#
0$
1'
0(
1-
1.
0/
12
03
17
1;
1=
1A
0B
b00100100 E
b1001 F
1H
b0000000010110110 J
1M
1Q
1R
0S
b0100100 V
1W
1[
#3188803752
0!
0#
0'
0-
0.
02
0;
0A
0M
0R
#3233092693
1!
1#
1'
1-
1.
12
07
1;
0=
1A
b00100101 E
0I
1M
0Q
1R
b0100101 V
0X
0[
#3277381634
0!
0#
0'
0-
0.
02
0;
0A
0M
0R
#3321670575
1!
1#
1$
1&
1'
1(
b1 +
1-
1.
1/
11
12
13
1;
1A
1B
1D
b00100110 E
0H
1M
1R
1S
b0100110 V
0W
#3365959516
0!
0#
0'
0-
0.
02
0;
0A
0M
0R
#3410248457
1!
1#
1'
1-
1.
12
1;
1A
b00100111 E
1I
1M
1R
b0100111 V
1X
#3454537398
0!
0#
0'
0-
0.
02
0;
0A
0M
0R
#3498826339
1!
1#
0$
1'
0(
1-
1.
0/
12
03
17
1;
1=
1A
0B
b00101000 E
b1010 F
1H
b0000000101101101 J
1M
1Q
1R
0S
b0101000 V
1W
1[
#3543115280
0!
0#
0'
0-
0.
02
0;
0A
0M
0R
#3587404221
1!
1#
1'
1-
1.
12
07
1;
0=
1A
b00101001 E
0I
1M
0Q
1R
b0101001 V
0X
0[
#3631693162
0!
0#
0'
0-
0.
02
0;
0A
0M
0R
#3675982103
1!
1#
1$
1'
1(
b10 +
1-
1.
1/
12
13
1;
1A
1B
b00101010 E
0H
1M
1R
1S
b0101010 V
0W
#3720271044
0!
0#
0'
0-
0.
02
0;
0A
0M
0R
#3764559985
1!
1#
1'
1-
1.
12
1;
1A
b00101011 E
1I
1M
1R
b0101011 V
1X
#3808848926
0!
0#
0'
0-
0.
02
0;
0A
0M
0R
#3853137867
1!
1#
0$
1'
0(
1-
1.
0/
12
03
17
1;
1=
1A
0B
b00101100 E
b1011 F
1H
b0000001011011011 J
1M
1Q
1R
0S
b0101100 V
1W
1[
#3897426808
0!
0#
0'
0-
0.
02
0;
0A
0M
0R
#3941715749
1!
1#
1'
1-
1.
12
07
1;
0=
1A
b00101101 E
0I
1M
0Q
1R
b0101101 V
0X
0[
#3986004690
0!
0#
0'
0-
0.
02
0;
0A
0M
0R
#4030293631
1!
1#
1$
0&
1'
1(
b0 +
1-
1.
1/
01
12
13
1;
1A
1B
0D
b00101110 E
0H
1M
1R
1S
b0101110 V
0W
#4074582572
0!
0#
0'
0-
0.
02
0;
0A
0M
0R
#4118871513
1!
1#
1'
1-
1.
12
1;
1A
b00101111 E
1I
1M
1R
b0101111 V
1X
#4163160454
0!
0#
0'
0-
0.
02
0;
0A
0M
0R
#4207449395
1!
1#
0$
1'
0(
1-
1.
0/
12
03
17
1;
1=
1A
0B
b00110000 E
b1100 F
1H
b0000010110110110 J
1M
1Q
1R
0S
b0110000 V
1W
1[
#4251738336
0!
0#
0'
0-
0.
02
0;
0A
0M
0R
#4296027277
1!
1#
1'
1-
1.
12
07
1;
0=
1A
b00110001 E
0I
1M
0Q
1R
b0110001 V
0X
0[
#4340316218
0!
0#
0'
0-
0.
02
0;
0A
0M
0R
#4384605159
1!
1#
1$
1&
1'
1(
b1 +
1-
1.
1/
11
12
13
1;
1A
1B
1D
b00110010 E
0H
1M
1R
1S
b0110010 V
0W
#4428894100
0!
0#
0'
0-
0.
02
0;
0A
0M
0R
#4473183041
1!
1#
1'
1-
1.
12
1;
1A
b00110011 E
1I
1M
1R
b0110011 V
1X
#4517471982
0!
0#
0'
0-
0.
02
0;
0A
0M
0R
#4561760923
1!
1#
0$
1'
0(
1-
1.
0/
12
03
17
1;
1=
1A
0B
b00110100 E
b1101 F
1H
b0000101101101101 J
1M
1Q
1R
0S
b0110100 V
1W
1[
#4606049864
0!
0#
0'
0-
0.
02
0;
0A
0M
0R
#4650338805
1!
1#
1'
1-
1.
12
07
1;
0=
1A
b00110101 E
0I
1M
0Q
1R
b0110101 V
0X
0[
#4694627746
0!
0#
0'
0-
0.
02
0;
0A
0M
0R
#4738916687
1!
1#
1$
1'
1(
b10 +
1-
1.
1/
12
13
1;
1A
1B
b00110110 E
0H
1M
1R
1S
b0110110 V
0W
#4783205628
0!
0#
0'
0-
0.
02
0;
0A
0M
0R
#4827494569
1!
1#
1'
1-
1.
12
1;
1A
b00110111 E
1I
1M
1R
b0110111 V
1X
#4871783510
0!
0#
0'
0-
0.
02
0;
0A
0M
0R
#4916072451
1!
1#
0$
1'
0(
1-
1.
0/
12
03
17
1;
1=
1A
0B
b00111000 E
b1110 F
1H
b0001011011011011 J
1M
1Q
1R
0S
b0111000 V
1W
1[
#4960361392
0!
0#
0'
0-
0.
02
0;
0A
0M
0R
#5004650333
1!
1#
1'
1-
1.
12
07
1;
0=
1A
b00111001 E
0I
1M
0Q
1R
b0111001 V
0X
0[
#5048939274
0!
0#
0'
0-
0.
02
0;
0A
0M
0R
#5093228215
1!
1#
1$
0&
1'
1(
b0 +
1-
1.
1/
01
12
13
1;
1A
1B
0D
b00111010 E
0H
1M
1R
1S
b0111010 V
0W
#5137517156
0!
0#
0'
0-
0.
02
0;
0A
0M
0R
#5181806097
1!
1#
1'
1-
1.
12
1;
1A
b00111011 E
1I
1M
1R
b0111011 V
1X
#5226095038
0!
0#
0'
0-
0.
02
0;
0A
0M
0R
#5270383979
1!
1#
0$
1'
0(
1-
1.
0/
12
03
17
1;
1=
1A
0B
b00111100 E
b1111 F
1H
b0010110110110110 J
1M
1Q
1R
0S
b0111100 V
1W
1[
#5314672920
0!
0#
0'
0-
0.
02
0;
0A
0M
0R
#5358961861
1!
1#
1'
1-
1.
12
07
1;
0=
1A
b00111101 E
0I
1M
0Q
1R
b0111101 V
0X
0[
#5403250802
0!
0#
0'
0-
0.
02
0;
0A
0M
0R
#5447539743
1!
1#
1$
1&
1'
1(
b1 +
1-
1.
1/
11
12
13
1;
1A
1B
1D
b00111110 E
0H
1M
1R
1S
b0111110 V
0W
#5491828684
0!
0#
0'
0-
0.
02
0;
0A
0M
0R
#5536117625
1!
1#
1'
1-
1.
12
1;
1A
b00111111 E
1I
1M
1R
b0111111 V
1X
#5580406566
0!
0#
0'
0-
0.
02
0;
0A
0M
0R
#5624695507
1!
1#
0$
1%
1'
0(
1-
1.
0/
12
03
14
17
1;
1=
1A
0B
b01000000 E
b10000 F
1H
b0101101101101101 J
1M
1Q
1R
0S
1T
b1000000 V
1W
1[
#5668984448
0!
0#
0'
0-
0.
02
0;
0A
0M
0R
#5713273389
1!
1#
1'
1-
1.
12
07
1;
0=
1A
b01000001 E
0I
1M
0Q
1R
b1000001 V
0X
0[
#5757562330
0!
0#
0'
0-
0.
02
0;
0A
0M
0R
#5801851271
1!
1#
1$
1'
1(
b10 +
1-
1.
1/
12
13
1;
1A
1B
b01000010 E
0H
1M
1R
1S
b1000010 V
0W
#5846140212
0!
0#
0'
0-
0.
02
0;
0A
0M
0R
#5890429153
1!
1#
1'
1-
1.
12
1;
1A
b01000011 E
1I
1M
1R
b1000011 V
1X
#5934718094
0!
0#
0'
0-
0.
02
0;
0A
0M
0R
#5979007035
1!
1#
0$
1'
0(
1-
1.
0/
12
03
17
1;
1=
1A
0B
b01000100 E
b10001 F
1H
b1011011011011011 J
1M
1Q
1R
0S
b1000100 V
1W
1[
#6023295976
0!
0#
0'
0-
0.
02
0;
0A
0M
0R
#6067584917
1!
1#
1'
1-
1.
12
07
1;
0=
1A
b01000101 E
0I
1M
0Q
1R
b1000101 V
0X
0[
#6111873858
0!
0#
0'
0-
0.
02
0;
0A
0M
0R
#6156162799
1!
1#
1$
0&
1'
1(
b0 +
1-
1.
1/
01
12
13
1;
1A
1B
0D
b01000110 E
0H
1M
1R
1S
b1000110 V
0W
#6200451740
0!
0#
0'
0-
0.
02
0;
0A
0M
0R
#6244740681
1!
1#
1'
1-
1.
12
1;
1A
b01000111 E
1I
1M
1R
b1000111 V
1X
#6289029622
0!
0#
0'
0-
0.
02
0;
0A
0M
0R
#6333318563
1!
1#
0$
1'
0(
1-
1.
0/
12
03
16
17
b1011011011011011 9
1;
1=
1>
b1011011011011011 @
1A
0B
b01001000 E
b0 F
b1 G
1H
b0000000000000000 J
1K
1M
1N
b1011011011011011 P
1Q
1R
0S
b1001000 V
1W
1[
#6377607504
0!
0#
0'
0-
0.
02
0;
0A
0M
0R
#6421896445
1!
1#
1'
1-
1.
12
06
07
1;
0=
0>
1A
b01001001 E
0I
0K
1M
0N
0Q
1R
b1001001 V
0X
0[
1\
#6466185386
0!
0#
0'
0-
0.
02
0;
0A
0M
0R
#6510474327
1!
1#
1$
1&
1'
1(
b1 +
1-
1.
1/
11
12
13
1;
1A
1B
1D
b01001010 E
0H
1M
1R
1S
b1001010 V
0W
#6554763268
0!
0#
0'
0-
0.
02
0;
0A
0M
0R
#6599052209
1!
1#
1'
1-
1.
12
1;
1A
b01001011 E
1I
1M
1R
b1001011 V
1X
#6643341150
0!
0#
0'
0-
0.
02
0;
0A
0M
0R
#6687630091
1!
1#
0$
1'
0(
1*
1-
1.
0/
12
03
15
1;
1A
0B
b01001100 E
b1 F
1H
1M
1R
0S
1U
b1001100 V
1W
b1011011011011011 Y
b1 Z
0\
#6731919032
0!
0#
0'
0-
0.
02
0;
0A
0M
0R
#6776207973
1!
1#
1'
1-
1.
12
1;
1A
b01001101 E
0I
1M
1R
b1001101 V
0X
#6820496914
0!
0#
0'
0-
0.
02
0;
0A
0M
0R
#6864785855
1!
1#
1$
1'
1(
b10 +
1-
1.
1/
12
13
1;
1A
1B
b01001110 E
0H
1M
1R
1S
b1001110 V
0W
#6909074796
0!
0#
0'
0-
0.
02
0;
0A
0M
0R
#6953363737
1!
1#
1'
1-
1.
12
1;
1A
b01001111 E
1I
1M
1R
b1001111 V
1X
#6997652678
0!
0#
0'
0-
0.
02
0;
0A
0M
0R
#7041941619
1!
1#
0$
1'
0(
0*
1-
1.
0/
12
03
05
1;
1A
0B
b01010000 E
b10 F
1H
b0000000000000001 J
1M
1R
0S
0U
b1010000 V
1W
b0110110110110110 Y
b10 Z
#7086230560
0!
0#
0'
0-
0.
02
0;
0A
0M
0R
#7130519501
1!
1#
1'
1-
1.
12
1;
1A
b01010001 E
0I
1M
1R
b1010001 V
0X
#7174808442
0!
0#
0'
0-
0.
02
0;
0A
0M
0R
#7219097383
1!
1#
1$
0&
1'
1(
b0 +
1-
1.
1/
01
12
13
1;
1A
1B
0D
b01010010 E
0H
1M
1R
1S
b1010010 V
0W
#7263386324
0!
0#
0'
0-
0.
02
0;
0A
0M
0R
#7307675265
1!
1#
1'
1-
1.
12
1;
1A
b01010011 E
1I
1M
1R
b1010011 V
1X
#7351964206
0!
0#
0'
0-
0.
02
0;
0A
0M
0R
#7396253147
1!
1#
0$
1'
0(
1*
1-
1.
0/
12
03
15
1;
1A
0B
b01010100 E
b11 F
1H
b0000000000000010 J
1M
1R
0S
1U
b1010100 V
1W
b1101101101101100 Y
b11 Z
#7440542088
0!
0#
0'
0-
0.
02
0;
0A
0M
0R
#7484831029
1!
1#
1'
1-
1.
12
1;
1A
b01010101 E
0I
1M
1R
b1010101 V
0X
#7529119970
0!
0#
0'
0-
0.
02
0;
0A
0M
0R
#7573408911
1!
1#
1$
1&
1'
1(
b1 +
1-
1.
1/
11
12
13
1;
1A
1B
1D
b01010110 E
0H
1M
1R
1S
b1010110 V
0W
#7617697852
0!
0#
0'
0-
0.
02
0;
0A
0M
0R
#7661986793
1!
1#
1'
1-
1.
12
1;
1A
b01010111 E
1I
1M
1R
b1010111 V
1X
#7706275734
0!
0#
0'
0-
0.
02
0;
0A
0M
0R
